mousse/__init__.py
mousse/cache/__init__.py
mousse/cache/cache.py
mousse/cache/policies.py
mousse/cache/types.py
mousse/export/__init__.py
mousse/export/exporter.py
mousse/functional/__init__.py
mousse/functional/plugin.py
mousse/functional/pattern/__init__.py
mousse/functional/pattern/pattern.py
mousse/functional/pattern/types.py
mousse/functional/tools/__init__.py
mousse/functional/tools/functional.py
mousse/logger/__init__.py
mousse/logger/handler.py
mousse/logger/logger.py
mousse/pattern/__init__.py
mousse/pattern/mediator.py
mousse/pattern/object_pool.py
mousse/pattern/registry.py
mousse/pattern/singleton.py
mousse/types/__init__.py
mousse/types/accessor.py
mousse/types/config.py
mousse/types/custom.py
mousse/types/dataclass.py
mousse/types/field.py
mousse/types/parser.py
mousse/types/types.py
mousse/types/validator.py
mousse-0.1.41.dist-info/METADATA
mousse-0.1.41.dist-info/WHEEL
mousse-0.1.41.dist-info/top_level.txt
mousse-0.1.41.dist-info/RECORD
