Metadata-Version: 2.1
Name: mousse
Version: 0.1.41
Summary: mousse
Home-page: https://github.com/NgHoangDat/mousse.git
Author: nghoangdat
Author-email: 18.hoang.dat.12@gmail.com
License: UNKNOWN
Download-URL: https://github.com/NgHoangDat/mousse/archive/v0.1.41.tar.gz
Platform: UNKNOWN
Classifier: Programming Language :: Python :: 3
Classifier: License :: OSI Approved :: MIT License
Classifier: Operating System :: OS Independent
Requires-Python: >=3.6
Requires-Dist: dialga
Requires-Dist: toolz
Requires-Dist: pyyaml
Requires-Dist: python-dateutil
Provides-Extra: dev
Requires-Dist: black ; extra == 'dev'
Requires-Dist: jupyter ; extra == 'dev'
Requires-Dist: pytest ; extra == 'dev'
